setup.cfg
setup.py
t_sne_bhcuda/__init__.py
t_sne_bhcuda/bhtsne_cuda.py
t_sne_bhcuda/spike_heatmap.py
t_sne_bhcuda/t_sne_spikes.py
t_sne_bhcuda/tsne_cluster.py
t_sne_bhcuda.egg-info/PKG-INFO
t_sne_bhcuda.egg-info/SOURCES.txt
t_sne_bhcuda.egg-info/dependency_links.txt
t_sne_bhcuda.egg-info/not-zip-safe
t_sne_bhcuda.egg-info/top_level.txt