Metadata-Version: 1.0
Name: t-sne-bhcuda
Version: 0.2.1
Summary: T-sne with burnes hut and cuda extension (with python wrappers and python code for for spike sorting)
Home-page: https://github.com/georgedimitriadis/t_sne_bhcuda
Author: George Dimitriadis
Author-email: gdimitri@hotmail.com
License: MIT
Platform: UNKNOWN
